{
  "rowCount" : 20,
  "columns" : {
    "ib_income_band_sk" : {
      "distinctValuesCount" : 20,
      "nullsCount" : 0,
      "min" : 1,
      "max" : 20,
      "dataSize" : null
    },
    "ib_lower_bound" : {
      "distinctValuesCount" : 20,
      "nullsCount" : 0,
      "min" : 0,
      "max" : 190001,
      "dataSize" : null
    },
    "ib_upper_bound" : {
      "distinctValuesCount" : 20,
      "nullsCount" : 0,
      "min" : 10000,
      "max" : 200000,
      "dataSize" : null
    }
  }
}
